clivia/__init__.py
clivia/arguments.py
clivia/constants.py
clivia/data.py
clivia/prompt.py
clivia/terminal.py
clivia/text/__init__.py
clivia/text/align.py
clivia/text/core.py
clivia-1.0.0.dev1.dist-info/DESCRIPTION.rst
clivia-1.0.0.dev1.dist-info/METADATA
clivia-1.0.0.dev1.dist-info/RECORD
clivia-1.0.0.dev1.dist-info/WHEEL
clivia-1.0.0.dev1.dist-info/metadata.json
clivia-1.0.0.dev1.dist-info/top_level.txt
