Metadata-Version: 2.0
Name: clivia
Version: 1.0.0.dev1
Summary: A library for simple CLI development in Python
Home-page: https://github.com/chunkhang/clivia
Author: Marcus Mu
Author-email: chunkhang@gmail.com
License: UNLICENSE
Keywords: clivia
Platform: UNKNOWN
Classifier: Intended Audience :: Developers
Classifier: Environment :: Console
Classifier: Programming Language :: Python :: 3 :: Only
Requires-Python: >=3
